vefaas_browser_session/__init__.py
vefaas_browser_session/api_client.py
vefaas_browser_session/api_response.py
vefaas_browser_session/configuration.py
vefaas_browser_session/exceptions.py
vefaas_browser_session/py.typed
vefaas_browser_session/rest.py
vefaas_browser_session/api/__init__.py
vefaas_browser_session/api/browsers_api.py
vefaas_browser_session/models/__init__.py
vefaas_browser_session/models/browser_browser.py
vefaas_browser_session/models/browser_browser_meta.py
vefaas_browser_session/models/browser_browser_options.py
vefaas_browser_session/models/v1_create_browser_request.py
vefaas_browser_session/models/v1_error.py
vefaas_browser_session-0.0.1.dist-info/METADATA
vefaas_browser_session-0.0.1.dist-info/WHEEL
vefaas_browser_session-0.0.1.dist-info/top_level.txt
vefaas_browser_session-0.0.1.dist-info/RECORD
