Metadata-Version: 2.4
Name: vefaas_browser_session
Version: 0.0.1
Summary: veFaaS Browser Session Manager API
Home-page: 
Author: veFaaS API Support
Author-email: veFaaS API Support <support@vefaas.com>
License-Expression: MIT
Project-URL: Repository, https://github.com/GIT_USER_ID/GIT_REPO_ID
Keywords: OpenAPI,OpenAPI-Generator,veFaaS Browser Session Manager API
Requires-Python: >=3.9
Requires-Dist: urllib3<3.0.0,>=2.1.0
Requires-Dist: python-dateutil>=2.8.2
Requires-Dist: pydantic>=2
Requires-Dist: typing-extensions>=4.7.1
Dynamic: author
